Workbook

Sheet Historical Financials
A1: A | B1: B | C1: C | D1: D | E1: E | F1: F | G1: G | H1: H
A2: Financial Metric | B2: FY2023 - A | C2: FY2024 - A | D2: FY2025 - A | E2: FY2026 - A | F2: FY2027 - F | G2: FY2028 - F | H2: FY2029 - F
A3: Net Revenue | B3: 1020.4 | C3: 1776.1 | D3: 2098.9 | E3: 2502.8 | F3: =E3*(1+Ratios!E2) -> 2940.79 | G3: =F3*(1+Ratios!F2) -> 3440.7243 | H3: =G3*(1+Ratios!G2) -> 3991.2402
A4: Total Operating Expenses | B4: 580.1 | C4: 1126 | D4: 1370.7 | E4: 1912.1 | F4: 2283.19 | G4: 2702.12 | H4: 3170.13
A5: Operating Income | B5: 189.6 | C5: 650.1 | D5: 728.2 | E5: 590.7 | F5: 657.6 | G5: 738.62 | H5: 821.1
A6: Income Before Tax | B6: 176.7 | C6: 656.7 | D6: 717.5 | E6: 660.4
A7: Net Income | B7: 137.5 | C7: 501.5 | D7: 550.3 | E7: 498.7 | F7: 555.1 | G7: 623.5 | H7: 693.2
A8: Total Assets | B8: 14695.7 | C8: 19022.5 | D8: 24781.1 | E8: 33259.8
A9: Cash & Cash Equivalents | B9: 9480.2 | C9: 13245.7 | D9: 18066.3 | E9: 27802.2
A10: Total Debt | B10: 326.4 | C10: 256.1 | D10: 128.4 | E10: 334.7
A11: Total Liabilities | B11: 13983.6 | C11: 17857.4 | D11: 23043.7 | E11: 31334.6
A12: Shareholders' Equity | B12: 712.2 | C12: 1165.1 | D12: 1737.4 | E12: 1925.2
A13: Operating Cash Flow | B13: 4727.4 | C13: 4075.1 | D13: 5719.5 | E13: 7553.9 | F13: 857.1 | G13: 1033.2 | H13: 1237.3
A14: Capital Expenditure | B14: 10.6 | C14: 16.4 | D14: 45.3 | E14: 21.4 | F14: 29.41 | G14: 34.41 | H14: 39.91
A15: Free Cash Flow | B15: 188.1 | C15: 586.8 | D15: 742.2 | E15: 705.4 | F15: 827.4 | G15: 998 | H15: 1197.4

Sheet Ratios
A1: Ratio / Metric | B1: FY2024 | C1: FY2025 | D1: FY2026 | E1: FY2027 - F | F1: FY2028 - F | G1: FY2029 - F
A2: Revenue Growth | B2: ='Historical Financials'!C3/'Historical Financials'!B3-1 -> 0.74059192 | C2: =('Historical Financials'!D3-'Historical Financials'!C3)/'Historical Financials'!C3 -> 0.18174652 | D2: =('Historical Financials'!E3-'Historical Financials'!D3)/'Historical Financials'!D3 -> 0.19243413 | E2: 0.175 | F2: 0.17 | G2: 0.16
A3: Operating Profit Growth | B3: ='Historical Financials'!C5/'Historical Financials'!B5-1 -> 2.4287975 | C3: =('Historical Financials'!D5-'Historical Financials'!C5)/'Historical Financials'!C5 -> 0.12013536 | D3: =('Historical Financials'!E5-'Historical Financials'!D5)/'Historical Financials'!D5 -> -0.18882175
A4: Net Income Growth | B4: ='Historical Financials'!C7/'Historical Financials'!B7-1 -> 2.6472727 | C4: =('Historical Financials'!D7-'Historical Financials'!C7)/'Historical Financials'!C7 -> 0.097308076 | D4: =('Historical Financials'!E7-'Historical Financials'!D7)/'Historical Financials'!D7 -> -0.093767036
A5: Free Cash Flow Growth | B5: ='Historical Financials'!C15/'Historical Financials'!B15-1 -> 2.1196172 | C5: =('Historical Financials'!D15-'Historical Financials'!C15)/'Historical Financials'!C15 -> 0.26482618 | D5: =('Historical Financials'!E15-'Historical Financials'!D15)/'Historical Financials'!D15 -> -0.049582323
A6: Operating Margin | B6: ='Historical Financials'!C5/'Historical Financials'!C3 -> 0.36602669 | C6: ='Historical Financials'!D5/'Historical Financials'!D3 -> 0.34694364 | D6: ='Historical Financials'!E5/'Historical Financials'!E3 -> 0.23601566
A7: Net Profit Margin | B7: ='Historical Financials'!C7/'Historical Financials'!C3 -> 0.28236023 | C7: ='Historical Financials'!D7/'Historical Financials'!D3 -> 0.26218495 | D7: ='Historical Financials'!E7/'Historical Financials'!E3 -> 0.19925683

Sheet Drivers & Assumptions
A1: Driver | B1: Historical observation | C1: Forecast assumption | D1: Reason
A2: Customer growth | B2: Strong growth in customers | C2: 0.15 | D2: Continued geographic expansion
A3: Transaction volume | B3: Increasing as customers grow | C3: 0.18 | D3: Higher customer usage
A4: Geographic expansion | B4: Increasing | C4: continued exspansion | D4: Wise adding markets and licences
A5: Product usage | B5: Increasing | C5: Increasing | D5: Customers are using Wise for more everyday financial activity
A6: Pricing | B6: reduced prices over time - more competitive | C6: gradual reduction | D6: Lower prices can support customer and transaction growth
A8: FY2027 Scenario | B8: Bear | C8: Base | D8: Bull
A9: Revenue | B9: 2703.02 | C9: 2878.22 | D9: 3053.42
A10: Operating Margin | B10: 0.15 | C10: 0.2 | D10: 0.24
A11: Operating Profit | B11: 405.45 | C11: 575.64 | D11: 732.82
A12: Net Income* | B12: 305.35 | C12: 433.24 | D12: 551.14
A13: Capex | B13: 189.21 | C13: 143.91 | D13: 122.14
A14: Free Cash Flow* | B14: 667.89 | C14: 719.31 | D14: 798.87
